haruka_fs/provider/__init__.py
haruka_fs/provider/auto_provider.py
haruka_fs/provider/basic_provider.py
haruka_fs/provider/oss_provider.py
haruka_fs/provider/tos_provider.py
haruka_fs/utils/load_env.py
haruka_fs-0.1.6.dist-info/METADATA
haruka_fs-0.1.6.dist-info/WHEEL
haruka_fs-0.1.6.dist-info/RECORD
